{
  "$schema": "./node_modules/nx/schemas/workspace-schema.json",
  "version": 2,
  "projects": {
    "features-post": "libs/features/post",
    "features-shortcuts": "libs/features/shortcuts",
    "features-wysiwyg-editor": "libs/features/wysiwyg-editor",
    "react-hooks": "libs/react/hooks",
    "react-ui": "libs/react/ui",
    "web-dexiejs": "apps/web-dexiejs",
    "web-homebase": "apps/web-homebase",
    "web-instantdb": "apps/web-instantdb",
    "web-replicache": "apps/web-replicache",
    "web-rxdb": "apps/web-rxdb",
    "web-watermelondb": "apps/web-watermelondb"
  }
}
